<?xml version = '1.0' encoding = 'UTF-8'?>
<TableProxyOraclev12c class="oracle.dbtools.crest.model.design.storage.oracle.v12c.TableProxyOraclev12c" name="Sales_Order_Line_Attributes" directorySegmentName="seg_0" id="79AF998F-F95A-5F37-3F79-AA2AC6C95504">
<createdBy>Tom</createdBy>
<createdTime>2015-06-03 11:45:39 UTC</createdTime>
<ownerDesignName>DataModel v0.2</ownerDesignName>
<logging>YES</logging>
<partitionedRowMovement>DISABLE</partitionedRowMovement>
<temporaryChanged>false</temporaryChanged>
<accessDriverType>oracle_loader</accessDriverType>
<rejectLimit></rejectLimit>
<columnProxies itemClass="oracle.dbtools.crest.model.design.storage.oracle.v12c.ColumnProxyOraclev12c">
<ColumnProxy name="Sales_Order_Line_ID" id="037B545E-35A3-9631-F601-CA28E0426456">
<createdBy>Tom</createdBy>
<createdTime>2015-06-03 11:49:18 UTC</createdTime>
<ownerDesignName>DataModel v0.2</ownerDesignName>
</ColumnProxy>
<ColumnProxy name="Created_Date" id="07830D26-1D55-C9C7-D75B-5801C9AD7513">
<createdBy>edelweiss.kammermann</createdBy>
<createdTime>2015-06-09 12:30:07 UTC</createdTime>
<ownerDesignName>DataModel v0.2</ownerDesignName>
</ColumnProxy>
<ColumnProxy name="Attribute_ID" id="73135747-ED87-BB40-C6D6-F2B12B25069B">
<createdBy>Tom</createdBy>
<createdTime>2015-06-03 11:47:52 UTC</createdTime>
<ownerDesignName>DataModel v0.2</ownerDesignName>
</ColumnProxy>
<ColumnProxy name="Updated_Date" id="80AFB6F3-F442-0856-786F-12EA46764931">
<createdBy>edelweiss.kammermann</createdBy>
<createdTime>2015-06-09 12:30:07 UTC</createdTime>
<ownerDesignName>DataModel v0.2</ownerDesignName>
</ColumnProxy>
<ColumnProxy name="Sales_Order_Line_Attributes_ID" id="8E033CF6-81D3-887C-3BE9-00C2CDB4B17A">
<createdBy>Tom</createdBy>
<createdTime>2015-06-03 11:46:31 UTC</createdTime>
<ownerDesignName>DataModel v0.2</ownerDesignName>
</ColumnProxy>
<ColumnProxy name="Product_Attribute_ID" id="FA514422-78A4-C978-5035-232D165033C6">
<createdBy>Tom</createdBy>
<createdTime>2015-06-03 11:49:18 UTC</createdTime>
<ownerDesignName>DataModel v0.2</ownerDesignName>
</ColumnProxy>
</columnProxies>
<foreignKeys>
<ForeignKey class="oracle.dbtools.crest.model.design.storage.oracle.v10g.FKProxyOraclev10g" name="SOLA_ATTR_FK" id="0F652C29-A4CF-02A0-0D32-BC5ED12956E6">
<createdBy>Tom</createdBy>
<createdTime>2015-06-03 11:47:52 UTC</createdTime>
<ownerDesignName>DataModel v0.2</ownerDesignName>
</ForeignKey>
<ForeignKey class="oracle.dbtools.crest.model.design.storage.oracle.v10g.FKProxyOraclev10g" name="SOLA_PA_FK" id="355C2139-03D5-C5B8-D005-F7E28E68DAD3">
<createdBy>Tom</createdBy>
<createdTime>2015-06-03 11:49:18 UTC</createdTime>
<ownerDesignName>DataModel v0.2</ownerDesignName>
</ForeignKey>
<ForeignKey class="oracle.dbtools.crest.model.design.storage.oracle.v10g.FKProxyOraclev10g" name="SOLA_SOL_FK" id="EE903361-563F-257F-2855-004DBD9E517D">
<createdBy>Tom</createdBy>
<createdTime>2015-06-03 11:49:18 UTC</createdTime>
<ownerDesignName>DataModel v0.2</ownerDesignName>
</ForeignKey>
</foreignKeys>
<primaryKeys>
<PrimaryKey class="oracle.dbtools.crest.model.design.storage.oracle.v10g.PKProxyOraclev10g" name="Sales_Order_Line_Attributes_PK" id="E7EFC2BA-8F3A-6518-EFB2-9A0A009F452C">
<createdBy>Tom</createdBy>
<createdTime>2015-06-03 11:46:31 UTC</createdTime>
<ownerDesignName>DataModel v0.2</ownerDesignName>
<indexSort>SORTED</indexSort>
</PrimaryKey>
</primaryKeys>
</TableProxyOraclev12c>