<?xml version = '1.0' encoding = 'UTF-8'?>
<TableProxyOraclev12c class="oracle.dbtools.crest.model.design.storage.oracle.v12c.TableProxyOraclev12c" name="Returns" directorySegmentName="seg_0" id="EB13E6C4-F4B5-B506-4125-BBE1B5DFA1CA">
<createdBy>Adam</createdBy>
<createdTime>2015-05-18 09:04:19 UTC</createdTime>
<ownerDesignName>DataModel v0.2</ownerDesignName>
<logging>YES</logging>
<partitionedRowMovement>DISABLE</partitionedRowMovement>
<temporaryChanged>false</temporaryChanged>
<accessDriverType>oracle_loader</accessDriverType>
<rejectLimit></rejectLimit>
<columnProxies itemClass="oracle.dbtools.crest.model.design.storage.oracle.v12c.ColumnProxyOraclev12c">
<ColumnProxy name="Return_Date" id="5F29BDDD-9698-8B61-2896-223CBE3CCA6C">
<createdBy>Adam</createdBy>
<createdTime>2015-05-18 09:04:19 UTC</createdTime>
<ownerDesignName>DataModel v0.2</ownerDesignName>
</ColumnProxy>
<ColumnProxy name="Created_Date" id="70AB64DA-8406-E416-EB06-5AB43A64442D">
<createdBy>edelweiss.kammermann</createdBy>
<createdTime>2015-06-09 12:30:07 UTC</createdTime>
<ownerDesignName>DataModel v0.2</ownerDesignName>
</ColumnProxy>
<ColumnProxy name="Return_id" id="9700E626-811E-3D22-2656-AD9D127356A5">
<createdBy>Adam</createdBy>
<createdTime>2015-05-18 09:04:19 UTC</createdTime>
<ownerDesignName>DataModel v0.2</ownerDesignName>
</ColumnProxy>
<ColumnProxy name="Return_Comment" id="E533A297-8468-DF4F-A4D6-5884CC9FAEAD">
<createdBy>Adam</createdBy>
<createdTime>2015-05-18 09:04:19 UTC</createdTime>
<ownerDesignName>DataModel v0.2</ownerDesignName>
</ColumnProxy>
<ColumnProxy name="Updated_Date" id="ECC60A8C-7228-8743-138C-675C4C4BD3FF">
<createdBy>edelweiss.kammermann</createdBy>
<createdTime>2015-06-09 12:30:07 UTC</createdTime>
<ownerDesignName>DataModel v0.2</ownerDesignName>
</ColumnProxy>
<ColumnProxy name="Invoice_Line_Item_ID" id="F82A7D7C-1957-F518-0B14-9334F8BA69B1">
<createdBy>Adam</createdBy>
<createdTime>2015-05-18 09:04:19 UTC</createdTime>
<ownerDesignName>DataModel v0.2</ownerDesignName>
</ColumnProxy>
</columnProxies>
<foreignKeys>
<ForeignKey class="oracle.dbtools.crest.model.design.storage.oracle.v10g.FKProxyOraclev10g" name="Returns_Invoice_Line_Items_FK" id="4F37470D-BBFE-0A67-3EB8-9E6DB92140E4">
<createdBy>Adam</createdBy>
<createdTime>2015-05-18 09:04:19 UTC</createdTime>
<ownerDesignName>DataModel v0.2</ownerDesignName>
</ForeignKey>
</foreignKeys>
<primaryKeys>
<PrimaryKey class="oracle.dbtools.crest.model.design.storage.oracle.v10g.PKProxyOraclev10g" name="Returns_PK" id="4870994E-E1B6-B462-F450-1309022E70B8">
<createdBy>Adam</createdBy>
<createdTime>2015-05-18 09:04:19 UTC</createdTime>
<ownerDesignName>DataModel v0.2</ownerDesignName>
<indexSort>SORTED</indexSort>
</PrimaryKey>
</primaryKeys>
</TableProxyOraclev12c>